pyHydrabus/__init__.py
pyHydrabus/auxpin.py
pyHydrabus/ccdbg.py
pyHydrabus/common.py
pyHydrabus/hydrabus.py
pyHydrabus/i2c.py
pyHydrabus/mmc.py
pyHydrabus/nfc.py
pyHydrabus/onewire.py
pyHydrabus/protocol.py
pyHydrabus/rawwire.py
pyHydrabus/sdio.py
pyHydrabus/smartcard.py
pyHydrabus/spi.py
pyHydrabus/swd.py
pyHydrabus/uart.py
pyHydrabus/utils.py
pyHydrabus-0.2.8.dist-info/LICENSE
pyHydrabus-0.2.8.dist-info/METADATA
pyHydrabus-0.2.8.dist-info/WHEEL
pyHydrabus-0.2.8.dist-info/top_level.txt
pyHydrabus-0.2.8.dist-info/RECORD
