Metadata-Version: 2.1
Name: pyHydrabus
Version: 0.2.8
Summary: Hydrabus BBIO python bindings
Home-page: https://github.com/hydrabus/pyhydrabus
Author: Baldanos
Author-email: balda@balda.ch
Classifier: Programming Language :: Python :: 3
Classifier: License :: OSI Approved :: Apache Software License
Classifier: Operating System :: OS Independent
License-File: LICENSE
Requires-Dist: pyserial
